qgmap/__init__.py
qgmap/example.py
qgmap/geocoder.py
qgmap/presets.py
qgmap/qgmap.html
qgmap/qgmap.js
qgmap/qgmap_test.py
qgmap/qt.py
qgmap/tracer.py
qgmap-1.1.0.dist-info/LICENSE
qgmap-1.1.0.dist-info/METADATA
qgmap-1.1.0.dist-info/WHEEL
qgmap-1.1.0.dist-info/entry_points.txt
qgmap-1.1.0.dist-info/top_level.txt
qgmap-1.1.0.dist-info/RECORD
