Metadata-Version: 2.1
Name: qgmap
Version: 1.1.0
Summary: Interactive map widget for PySyde/PyQt4
Author-email: David García Garzón <voki@canvoki.net>
License: GNU GENERAL PUBLIC LICENSE
Project-URL: Homepage, https://github.com/vokimon/python-qgmap
Project-URL: Documentation, https://github.com/vokimon/python-qgmap
Project-URL: Repository, https://github.com/vokimon/python-qgmap
Project-URL: Changelog, https://github.com/vokimon/python-qgmap/blob/master/CHANGELOG.md
Keywords: maps,qt,pyside,pyqt
Classifier: Programming Language :: Python
Classifier: Programming Language :: Python :: 3
Classifier: Topic :: Scientific/Engineering :: GIS
Classifier: Topic :: Software Development :: Libraries :: Python Modules
Classifier: Environment :: X11 Applications :: Qt
Classifier: Environment :: Win32 (MS Windows)
Classifier: Intended Audience :: Developers
Classifier: Development Status :: 5 - Production/Stable
Classifier: License :: OSI Approved :: GNU General Public License v3 or later (GPLv3+)
Classifier: Operating System :: OS Independent
Requires-Python: >=3.10
License-File: LICENSE
Requires-Dist: pyside6
Requires-Dist: decorator
Requires-Dist: pytest
Requires-Dist: pytest-cov
